odoo8_addon_mail_restrict_follower_selection-8.0.1.0.0.99.dev10-py2.7-nspkg.pth
odoo8_addon_mail_restrict_follower_selection-8.0.1.0.0.99.dev10.dist-info/METADATA
odoo8_addon_mail_restrict_follower_selection-8.0.1.0.0.99.dev10.dist-info/RECORD
odoo8_addon_mail_restrict_follower_selection-8.0.1.0.0.99.dev10.dist-info/WHEEL
odoo8_addon_mail_restrict_follower_selection-8.0.1.0.0.99.dev10.dist-info/namespace_packages.txt
odoo8_addon_mail_restrict_follower_selection-8.0.1.0.0.99.dev10.dist-info/top_level.txt
odoo_addons/mail_restrict_follower_selection/README.rst
odoo_addons/mail_restrict_follower_selection/__init__.py
odoo_addons/mail_restrict_follower_selection/__openerp__.py
odoo_addons/mail_restrict_follower_selection/data/ir_actions.xml
odoo_addons/mail_restrict_follower_selection/data/ir_config_parameter.xml
odoo_addons/mail_restrict_follower_selection/i18n/de.po
odoo_addons/mail_restrict_follower_selection/i18n/es.po
odoo_addons/mail_restrict_follower_selection/i18n/es_CO.po
odoo_addons/mail_restrict_follower_selection/i18n/fr.po
odoo_addons/mail_restrict_follower_selection/i18n/mail_restrict_follower_selection.pot
odoo_addons/mail_restrict_follower_selection/i18n/pt_BR.po
odoo_addons/mail_restrict_follower_selection/i18n/sl.po
odoo_addons/mail_restrict_follower_selection/models/__init__.py
odoo_addons/mail_restrict_follower_selection/models/mail_wizard_invite.py
odoo_addons/mail_restrict_follower_selection/static/description/icon.png
odoo_addons/mail_restrict_follower_selection/tests/__init__.py
odoo_addons/mail_restrict_follower_selection/tests/test_mail_restrict_follower_selection.py
